daisyft/__init__.py
daisyft/py.typed
daisyft/cli/__init__.py
daisyft/cli/build.py
daisyft/cli/dev.py
daisyft/cli/init.py
daisyft/cli/main.py
daisyft/cli/run.py
daisyft/cli/sync.py
daisyft/templates/__init__.py
daisyft/templates/daisyft.toml.jinja2
daisyft/templates/input.css.jinja2
daisyft/templates/main.py.jinja2
daisyft/utils/README.md
daisyft/utils/__init__.py
daisyft/utils/command_utils.py
daisyft/utils/config.py
daisyft/utils/console.py
daisyft/utils/downloader.py
daisyft/utils/platform.py
daisyft/utils/process.py
daisyft/utils/release_info.py
daisyft/utils/template.py
daisyft/utils/toml_config.py
daisyft-0.1.8.dist-info/METADATA
daisyft-0.1.8.dist-info/WHEEL
daisyft-0.1.8.dist-info/entry_points.txt
daisyft-0.1.8.dist-info/licenses/LICENSE
daisyft-0.1.8.dist-info/RECORD
