Metadata-Version: 2.4
Name: daisyft
Version: 0.1.8
Summary: DaisyUI/Tailwind cli for FastHTML projects
Project-URL: Homepage, https://daisyft.com
Project-URL: Source, https://github.com/banditburai/daisyft
Project-URL: Bug Tracker, https://github.com/banditburai/daisyft/issues
Author-email: firefly <promptsiren@gmail.com>
License: MIT
License-File: LICENSE
Keywords: components,daisyui,fasthtml,tailwind,ui,web
Classifier: Development Status :: 4 - Beta
Classifier: Intended Audience :: Developers
Classifier: License :: OSI Approved :: MIT License
Classifier: Programming Language :: Python :: 3
Classifier: Programming Language :: Python :: 3.11
Classifier: Topic :: Internet :: WWW/HTTP
Classifier: Topic :: Software Development :: Libraries :: Python Modules
Requires-Python: >=3.11
Requires-Dist: jinja2>=3.1.5
Requires-Dist: python-fasthtml>=0.12.0
Requires-Dist: questionary>=2.1.0
Requires-Dist: requests>=2.32.3
Requires-Dist: rich>=13.9.4
Requires-Dist: tomli-w>=1.0.0
Requires-Dist: tomli>=2.0.1
Requires-Dist: typer>=0.15.1
